nonebot_plugin_remind/__init__.py
nonebot_plugin_remind/colloquial.py
nonebot_plugin_remind/common.py
nonebot_plugin_remind/config.py
nonebot_plugin_remind/data_sourse.py
nonebot_plugin_remind/glm4.py
nonebot_plugin_remind/parse.py
nonebot_plugin_remind/utils.py
nonebot_plugin_remind-0.1.10.dist-info/LICENSE
nonebot_plugin_remind-0.1.10.dist-info/METADATA
nonebot_plugin_remind-0.1.10.dist-info/WHEEL
nonebot_plugin_remind-0.1.10.dist-info/RECORD
