Metadata-Version: 2.3
Name: nonebot-plugin-remind
Version: 0.1.10
Summary: nonebot2插件：提供符合中国宝宝体质的定时提醒功能~
License: MIT
Author: Elden
Author-email: h_elden@qq.com
Requires-Python: >=3.9
Classifier: License :: OSI Approved :: MIT License
Classifier: Programming Language :: Python :: 3
Classifier: Programming Language :: Python :: 3.9
Classifier: Programming Language :: Python :: 3.10
Classifier: Programming Language :: Python :: 3.11
Classifier: Programming Language :: Python :: 3.12
Classifier: Programming Language :: Python :: 3.13
Requires-Dist: jsonpickle (>=4.0.2,<4.1.0)
Requires-Dist: nonebot-adapter-onebot (>=2.4.6,<3.0.0)
Requires-Dist: nonebot-plugin-apscheduler (>=0.5.0,<0.6.0)
Requires-Dist: nonebot-plugin-localstore (>=0.7.3,<0.8.0)
Requires-Dist: nonebot2 (>=2.3.0,<3.0.0)
Requires-Dist: zhipuai (>=2.1.5,<2.2.0)
